ctyunsdk_bandwidth20220909/__init__.py
ctyunsdk_bandwidth20220909/bandwidth_client.py
ctyunsdk_bandwidth20220909/models/__init__.py
ctyunsdk_bandwidth20220909/models/v4_bandwidth_associate_eip.py
ctyunsdk_bandwidth20220909/models/v4_bandwidth_create.py
ctyunsdk_bandwidth20220909/models/v4_bandwidth_delete.py
ctyunsdk_bandwidth20220909/models/v4_bandwidth_disassociate_eip.py
ctyunsdk_bandwidth20220909-2.0.0.dist-info/licenses/LICENSE.txt
ctyunsdk_bandwidth20220909-2.0.0.dist-info/METADATA
ctyunsdk_bandwidth20220909-2.0.0.dist-info/WHEEL
ctyunsdk_bandwidth20220909-2.0.0.dist-info/top_level.txt
ctyunsdk_bandwidth20220909-2.0.0.dist-info/RECORD
